{
  "version": "5",
  "dialect": "pg",
  "entries": [
    {
      "idx": 0,
      "version": "5",
      "when": 1709299964709,
      "tag": "0000_soft_zeigeist",
      "breakpoints": true
    },
    {
      "idx": 1,
      "version": "7",
      "when": 1736448818884,
      "tag": "0001_wonderful_ender_wiggin",
      "breakpoints": true
    },
    {
      "idx": 2,
      "version": "7",
      "when": 1736449004223,
      "tag": "0002_colorful_la_nuit",
      "breakpoints": true
    },
    {
      "idx": 3,
      "version": "7",
      "when": 1740212527558,
      "tag": "0003_crazy_morph",
      "breakpoints": true
    },
    {
      "idx": 4,
      "version": "7",
      "when": 1740225792405,
      "tag": "0004_silky_gamora",
      "breakpoints": true
    },
    {
      "idx": 5,
      "version": "7",
      "when": 1740495235547,
      "tag": "0005_many_colonel_america",
      "breakpoints": true
    },
    {
      "idx": 6,
      "version": "7",
      "when": 1741020960757,
      "tag": "0006_good_ben_parker",
      "breakpoints": true
    },
    {
      "idx": 7,
      "version": "7",
      "when": 1744903258892,
      "tag": "0007_low_maverick",
      "breakpoints": true
    },
    {
      "idx": 8,
      "version": "7",
      "when": 1744985096624,
      "tag": "0008_foamy_machine_man",
      "breakpoints": true
    }
  ]
}